agent_torch-0.6.0.dist-info/METADATA
agent_torch-0.6.0.dist-info/WHEEL
agent_torch-0.6.0.dist-info/entry_points.txt
agent_torch-0.6.0.dist-info/licenses/LICENSE.md
agent_torch/__init__.py
agent_torch/core/__init__.py
agent_torch/core/analyzer/agent_graph.py
agent_torch/core/analyzer/agent_helpers.py
agent_torch/core/analyzer/datamodels.py
agent_torch/core/analyzer/retriever.py
agent_torch/core/analyzer/simulation_analyzer.py
agent_torch/core/analyzer/utils.py
agent_torch/core/config.py
agent_torch/core/controller.py
agent_torch/core/dataloader.py
agent_torch/core/decorators.py
agent_torch/core/distributions/README.md
agent_torch/core/distributions/__init__.py
agent_torch/core/distributions/distributions.py
agent_torch/core/environment.py
agent_torch/core/executor.py
agent_torch/core/helpers/__init__.py
agent_torch/core/helpers/distributions.py
agent_torch/core/helpers/environment.py
agent_torch/core/helpers/general.py
agent_torch/core/helpers/initializer.py
agent_torch/core/helpers/soft.py
agent_torch/core/initializer.py
agent_torch/core/llm/agent_memory.py
agent_torch/core/llm/archetype.py
agent_torch/core/llm/backend.py
agent_torch/core/llm/behavior.py
agent_torch/core/llm/prompt_manager.py
agent_torch/core/registry.py
agent_torch/core/runner.py
agent_torch/core/substep.py
agent_torch/core/utils.py
agent_torch/core/version.py
agent_torch/core/visualize.py
agent_torch/data/census/census_loader.py
agent_torch/data/census/generate/address.py
agent_torch/data/census/generate/base_pop.py
agent_torch/data/census/generate/household.py
agent_torch/data/census/generate/mobility_network.py
agent_torch/models/__init__.py
agent_torch/models/covid/calibration/__init__.py
agent_torch/models/covid/calibration/calibnn.py
agent_torch/models/covid/calibration/model_utils.py
agent_torch/models/covid/calibration/utils/__init__.py
agent_torch/models/covid/calibration/utils/data.py
agent_torch/models/covid/calibration/utils/feature.py
agent_torch/models/covid/calibration/utils/infection.py
agent_torch/models/covid/calibration/utils/llm.py
agent_torch/models/covid/calibration/utils/misc.py
agent_torch-0.6.0.dist-info/RECORD
