Metadata-Version: 2.1
Name: agent_torch
Version: 0.6.0
Summary: large population models
Author: Ayush Chopra
Maintainer: Ayush Chopra, Vedant Kulkarni
License: MIT
Project-URL: Homepage, https://lpm.media.mit.edu/docs
Project-URL: Issues, https://github.com/AgentTorch/AgentTorch/issues
Requires-Python: >=3.8
Requires-Dist: numpy>=1.24.3
Requires-Dist: pandas>=1.5.0
Requires-Dist: torch>=2.1.2
Requires-Dist: torch_geometric>=2.5.3
Requires-Dist: omegaconf>=2.3.0
Requires-Dist: asyncio>=3.4.3
Requires-Dist: langchain>=0.2.3
Requires-Dist: langchain-openai>=0.1.8
Requires-Dist: networkx>=3.0
Requires-Dist: tqdm>=4.66.4
Requires-Dist: dspy>=0.1.5
Requires-Dist: dask>=2024.12.1
